numbertypes.py
NumberTypes-0.1.dist-info/METADATA
NumberTypes-0.1.dist-info/WHEEL
NumberTypes-0.1.dist-info/top_level.txt
NumberTypes-0.1.dist-info/RECORD
