Metadata-Version: 2.1
Name: NumberTypes
Version: 0.1
Summary: Python Module to identify type of a number quickly and easily
Home-page: UNKNOWN
Author: Aryansh Gupta (AryanshDev)
Author-email: Aryanshappmaker@gmail.com
License: MIT
Keywords: numbers,helper,number types,number type,math
Platform: UNKNOWN
Requires-Python: >=3.1
